[
    {
        "title": "Apple Sends Lock Screen Alerts to Outdated iPhones Over Active Web-Based Exploits",
        "source": "The Hacker News",
        "time": "2026-03-28",
        "category": "\ue802Mar 27, 2026Spyware / Mobile Security",
        "link": "https://thehackernews.com/2026/03/apple-sends-lock-screen-alerts-to.html"
    },
    {
        "title": "TeamPCP Pushes Malicious Telnyx Versions to PyPI, Hides Stealer in WAV Files",
        "source": "The Hacker News",
        "time": "2026-03-28",
        "category": "\ue802Mar 27, 2026Cybersecurity / Malware",
        "link": "https://thehackernews.com/2026/03/teampcp-pushes-malicious-telnyx.html"
    },
    {
        "title": "Open VSX Bug Let Malicious VS Code Extensions Bypass Pre-Publish Security Checks",
        "source": "The Hacker News",
        "time": "2026-03-28",
        "category": "\ue802Mar 27, 2026Software Security / DevSecOps",
        "link": "https://thehackernews.com/2026/03/open-vsx-bug-let-malicious-vs-code.html"
    },
    {
        "title": "2026 Annual Threat Report: A Defender\u2019s Playbook From the Front Lines",
        "source": "The Hacker News",
        "time": "2026-03-28",
        "category": "SentinelOneEnterprise Security / Cloud Security",
        "link": "https://thehackernews.uk/sentinelone-threat-report"
    },
    {
        "title": "AitM Phishing Targets TikTok Business Accounts Using Cloudflare Turnstile Evasion",
        "source": "The Hacker News",
        "time": "2026-03-28",
        "category": "\ue802Mar 27, 2026Ransomware / Malware",
        "link": "https://thehackernews.com/2026/03/aitm-phishing-targets-tiktok-business.html"
    },
    {
        "title": "We Are At War",
        "source": "The Hacker News",
        "time": "2026-03-28",
        "category": "\ue802Mar 27, 2026Hacktivism / Threat Intelligence",
        "link": "https://thehackernews.com/2026/03/we-are-at-war.html"
    },
    {
        "title": "Inside the 2026 Cyber Workforce: Skills, Shortages, and Shifts in the Age of AI",
        "source": "The Hacker News",
        "time": "2026-03-28",
        "category": "SANS InstituteCybersecurity / Training",
        "link": "https://thehackernews.uk/sans-cyber-research"
    },
    {
        "title": "Bearlyfy Hits Russian Firms with Custom GenieLocker Ransomware",
        "source": "The Hacker News",
        "time": "2026-03-28",
        "category": "\ue802Mar 27, 2026Threat Intelligence / Vulnerability",
        "link": "https://thehackernews.com/2026/03/bearlyfy-hits-70-russian-firms-with.html"
    }
]